chatweaver/__init__.py
chatweaver/chat_weaver.py
chatweaver/__pycache__/__init__.cpython-312.pyc
chatweaver/__pycache__/__init__.cpython-313.pyc
chatweaver/__pycache__/app.cpython-312.pyc
chatweaver/__pycache__/chat_weaver.cpython-312.pyc
chatweaver/__pycache__/chat_weaver.cpython-313.pyc
chatweaver/__pycache__/hello.cpython-312.pyc
chatweaver/data/__init__.py
chatweaver/data/models.py
chatweaver/data/rules.py
chatweaver/data/__pycache__/__init__.cpython-312.pyc
chatweaver/data/__pycache__/__init__.cpython-313.pyc
chatweaver/data/__pycache__/models.cpython-312.pyc
chatweaver/data/__pycache__/models.cpython-313.pyc
chatweaver/data/__pycache__/rules.cpython-312.pyc
chatweaver/data/__pycache__/rules.cpython-313.pyc
chatweaver-1.1.0.dist-info/licenses/LICENCE
chatweaver-1.1.0.dist-info/METADATA
chatweaver-1.1.0.dist-info/WHEEL
chatweaver-1.1.0.dist-info/top_level.txt
chatweaver-1.1.0.dist-info/RECORD
