Metadata-Version: 2.4
Name: chatweaver
Version: 1.1.0
Summary: A Python library that simplifies building AI-driven chatbots with OpenAI, offering conversation management, file attachments, and persistent storage in one cohesive package.
Author-email: Cecchelani Diego <ceccdieg@gmail.com>
License-Expression: MIT
Project-URL: Homepage, https://www.chatweaver.it
Classifier: Programming Language :: Python :: 3
Classifier: Operating System :: OS Independent
Classifier: Development Status :: 4 - Beta
Classifier: Intended Audience :: Developers
Classifier: Topic :: Software Development :: Libraries :: Python Modules
Classifier: Topic :: Scientific/Engineering :: Artificial Intelligence
Requires-Python: >=3.10
License-File: LICENCE
Requires-Dist: openai==1.66.5
Dynamic: license-file
